cvpolation/__init__.py
cvpolation/code.py
cvpolation-1.0.1.dist-info/LICENSE
cvpolation-1.0.1.dist-info/METADATA
cvpolation-1.0.1.dist-info/WHEEL
cvpolation-1.0.1.dist-info/top_level.txt
cvpolation-1.0.1.dist-info/RECORD
