Metadata-Version: 2.1
Name: cvpolation
Version: 1.0.1
Summary: A package to get perform different interpolation techniques on an Image.
Home-page: https://github.com/toshihiroryuu/
Author: Athul Mathew Konoor
Author-email: athulmathewkonoor@gmail.com
License: UNKNOWN
Platform: UNKNOWN
Classifier: Programming Language :: Python :: 3
Classifier: License :: OSI Approved :: MIT License
Classifier: Operating System :: OS Independent
Requires-Python: >=3.6
Requires-Dist: prettytable (>=2.1.0)
Requires-Dist: Pillow (>=8.1.1)
